eagle200_reader/__init__.py
eagle200_reader/eagle200_reader.py
eagle200_reader-0.2.4.dist-info/LICENSE
eagle200_reader-0.2.4.dist-info/METADATA
eagle200_reader-0.2.4.dist-info/WHEEL
eagle200_reader-0.2.4.dist-info/top_level.txt
eagle200_reader-0.2.4.dist-info/RECORD
