Metadata-Version: 2.1
Name: eagle200-reader
Version: 0.2.4
Summary: A program to read from an Rainforest Eagle-200 on the local network
Home-page: https://github.com/gtdiehl/eagle200_reader
Author: UNKNOWN
Author-email: UNKNOWN
License: UNKNOWN
Platform: UNKNOWN
